Workbook

Sheet Saldo
B2: Valor para o mês | C2: Guilherme | E2: Stella
C3: =C5-C8-C10-C11-C22+C23+C7 -> 1732.8714 | E3: =E5-E8-E10-E11-E22+E23 -> 3729.3575
B5: Salário | C5: 10000 | E5: 10000
B6: Custos Totais | C6: =-SUM(C8,C10,C11) -> -7605.1286 | E6: =-SUM(E8,E10,E11) -> -5270.6425
B7: Resto o mês anterior
B8: Cartão Itaú | C8: =Itaú!E2 -> 40.161667 | E8: =Itaú!F2 -> 0
B9: Cartão NuBank | C9: =NuBank!E2 -> 5182.8969 | E9: =NuBank!F2 -> 1888.5725
B10: Compensasão no NuBank | C10: ='Compensasões e Transferências'!D4 -> 5182.8969 | E10: ='Compensasões e Transferências'!C4 -> 1888.5725
B11: Contas | C11: =Contas!B6 -> 2382.07 | E11: =Contas!B9 -> 3382.07
B12: Aluguel | C12: =Contas!K3 -> 1617.835 | E12: =Contas!K3 -> 1617.835
B13: Internet | C13: =Contas!K4 -> 222 | E13: =Contas!K4 -> 222
B14: Luz | C14: =Contas!K5 -> 180 | E14: =Contas!K5 -> 180
B15: Água | C15: =Contas!K6 -> 43.35 | E15: =Contas!K6 -> 43.35
B16: Gás | C16: =Contas!K7 -> 23 | E16: =Contas!K7 -> 23
B17: Seguranças+Câmera | C17: =Contas!$K9 -> 183.5 | E17: =Contas!K9 -> 183.5
B18: Cartão Itaú da Stella | E18: 1000
B19: Compensasões no cartão da Stella
B22: Dinheiro para NuConta | C22: 1000 | E22: 1000
B23: Dinheiro Guardado na poupança | C23: =SUM(C24:C35) -> 338 | E23: =SUM(E24:E33) -> 0
B24: Seu João | C24: =IF('NuConta e Poupança'!M5="Sim",'NuConta e Poupança'!N5,"")
B25: Seguro
B26: =" "&'NuConta e Poupança'!L7 | C26: =IF('NuConta e Poupança'!M7="Sim",'NuConta e Poupança'!N7,"")
B27: =" "&'NuConta e Poupança'!L8 -> Reembolso Psicóloga | C27: =IF('NuConta e Poupança'!M8="Sim",'NuConta e Poupança'!N8,"") -> 338
B28: =" "&'NuConta e Poupança'!L9 | C28: =IF('NuConta e Poupança'!M9="Sim",'NuConta e Poupança'!N9,"")
B29: =" "&'NuConta e Poupança'!L10 | C29: =IF('NuConta e Poupança'!M10="Sim",'NuConta e Poupança'!N10,"")
B30: =" "&'NuConta e Poupança'!L12 | C30: =IF('NuConta e Poupança'!M12="Sim",'NuConta e Poupança'!N11,"")
B31: =" "&'NuConta e Poupança'!L13 | C31: =IF('NuConta e Poupança'!M13="Sim",'NuConta e Poupança'!N12,"")
B32: =" "&'NuConta e Poupança'!L14 | C32: =IF('NuConta e Poupança'!M14="Sim",'NuConta e Poupança'!N13,"")
B33: =" "&'NuConta e Poupança'!L15 | C33: =IF('NuConta e Poupança'!M15="Sim",'NuConta e Poupança'!N14,"")
B34: =" "&'NuConta e Poupança'!L16 | C34: =IF('NuConta e Poupança'!M16="Sim",'NuConta e Poupança'!N15,"")
B35: =" "&'NuConta e Poupança'!L17 | C35: =IF('NuConta e Poupança'!M17="Sim",'NuConta e Poupança'!N16,"")
B36: =" "&'NuConta e Poupança'!L21 | C36: =IF('NuConta e Poupança'!M21="Sim",'NuConta e Poupança'!N20,"")
B37: =" "&'NuConta e Poupança'!L22 | C37: =IF('NuConta e Poupança'!M22="Sim",'NuConta e Poupança'!N21,"")

Sheet Compensasões e Transferências
C2: Stella | D2: Guilherme
B3: Cartão Itaú | C3: =Saldo!E8 -> 0 | D3: =Saldo!C8 -> 40.161667
B4: Cartão NuBank | C4: =Saldo!E9+C5 -> 1888.5725 | D4: =Saldo!C9+D5 -> 5182.8969
B10: Contas | C10: =SUM(C11,C13:C16) -> 2047.685
B11: Aluguel | C11: =Saldo!E12 -> 1617.835
B12: Vivo | C12: =Contas!K4 -> 222
B13: Luz | C13: =Contas!K5 -> 180
B14: Água | C14: =Contas!K6 -> 43.35
B15: Gás | C15: =Contas!K7 -> 23
B16: Seguranças+Câmera | C16: =Saldo!E17 -> 183.5
B17: Stella tem que transferir: | C17: =SUM(C3,C4,C5,C10) -> 3936.2575

Sheet Itaú
D1: Itaú Total | E1: Guilherme | F1: Stella | G1: Pais
D2: =SUM(L5:L21) -> 40.161667 | E2: =SUMIF($E$5:$E$29,E1,$M$5:$M$29) -> 40.161667 | F2: =SUMIF($F$5:$F$29,F1,$M$5:$M$29) -> 0 | G2: =SUMIF($G$5:$G$29,G1,$M$5:$M$29) -> 0
C4: Data de compra | D4: Descrição | E4: Responsável 1 | F4: Responsável 2 | G4: Responsável 3 | H4: Divisão | I4: Valor Total | J4: Modo de pagamento | K4: Categoria | L4: Valor da Parcela | M4: Valor por responsável | N4: Parcelas | O4: Primeira Parcela | P4: Última Parcela | Q4: Parcelas pagas (vira todo dia 10)
C5: ADIANTAR EM OUTUBRO | D5: Control Resonant | E5: Guilherme | H5: =COUNTA(E5:G5) -> 1 | I5: 240.97 | J5: Parcelado | K5: Jogos | L5: =I5/N5 -> 40.161667 | M5: =IFERROR(L5/H5,"") -> 40.161667 | N5: 6 | O5: 46237 | P5: =IF(N5<>1,EDATE(O5,N5-1),"") -> 46390 | Q5: =IF(O5<>"",IFERROR(DATEDIF(O5,TODAY(),"m")+1,""),"")
H6: =COUNTA(E6:G6) -> 0 | L6: =I6/N6 -> 0 | M6: =IFERROR(L6/H6,"") | N6: =(DATEDIF(O6,P6,"m")+1) -> 1 | Q6: =IF(O6<>"",IFERROR(DATEDIF(O6,TODAY(),"m")+1,""),"")
H7: =COUNTA(E7:G7) -> 0 | L7: =I7/N7 -> 0 | M7: =IFERROR(L7/H7,"") | N7: =(DATEDIF(O7,P7,"m")+1) -> 1
H8: =COUNTA(E8:G8) -> 0 | L8: =I8/N8 -> 0 | M8: =IFERROR(L8/H8,"") | N8: =(DATEDIF(O8,P8,"m")+1) -> 1
H9: =COUNTA(E9:G9) -> 0 | L9: =I9/N9 -> 0 | M9: =IFERROR(L9/H9,"") | N9: =(DATEDIF(O9,P9,"m")+1) -> 1
H10: =COUNTA(E10:G10) -> 0 | L10: =I10/N10 -> 0 | M10: =IFERROR(L10/H10,"") | N10: =(DATEDIF(O10,P10,"m")+1) -> 1 | Q10: =IF(O10<>"",IFERROR(DATEDIF(O10,TODAY(),"m")+1,""),"")
H11: =COUNTA(E11:G11) -> 0 | L11: =I11/N11 -> 0 | M11: =IFERROR(L11/H11,"") | N11: =(DATEDIF(O11,P11,"m")+1) -> 1
H12: =COUNTA(E12:G12) -> 0 | L12: =I12/N12 -> 0 | M12: =IFERROR(L12/H12,"") | N12: =(DATEDIF(O12,P12,"m")+1) -> 1
H13: =COUNTA(E13:G13) -> 0 | L13: =I13/N13 -> 0 | M13: =IFERROR(L13/H13,"") | N13: =(DATEDIF(O13,P13,"m")+1) -> 1
H14: =COUNTA(E14:G14) -> 0 | L14: =I14/N14 -> 0 | M14: =IFERROR(L14/H14,"") | N14: =(DATEDIF(O14,P14,"m")+1) -> 1
H15: =COUNTA(E15:G15) -> 0 | L15: =I15/N15 -> 0 | M15: =IFERROR(L15/H15,"") | N15: =(DATEDIF(O15,P15,"m")+1) -> 1

Sheet NuBank
D1: NuBank Total | E1: Guilherme | F1: Stella | G1: Pais
D2: =SUM(L6:L377) -> 7121.4694 | E2: =SUMIF($E$6:$E$377,E1,$M$6:$M$377) -> 5182.8969 | F2: =SUMIF($F$6:$F$377,F1,$M$6:$M$377) -> 1888.5725 | G2: =SUMIF($G$6:$G$377,G1,$M$6:$M$377) -> 0
D5: Descrição | E5: Responsável 1 | F5: Responsável 2 | G5: Responsável 3 | H5: Divisão | I5: Valor Total | J5: Modo de Pagamento | K5: Categoria | L5: Valor da Parcela | M5: Valor por responsável | N5: Parcelas | O5: Primeira Parcela | P5: Última Parcela | Q5: Parcelas pagas (vira todo dia 10)
D6: Manual | E6: Guilherme | H6: =COUNTA(E6:G6) -> 1 | I6: 258 | J6: Assinatura | K6: Assinaturas-Fixo | L6: =I6/N6 -> 86 | M6: =IFERROR(L6/H6,"") -> 86 | N6: 3 | O6: 46056 | P6: =IF(N6<>1,EDATE(O6,N6-1),"") -> 46115 | Q6: =IF(O6<>"",IFERROR(DATEDIF(O6,TODAY(),"m")+1,""),"") -> 6
D7: Muay Thai | E7: Guilherme | H7: =COUNTA(E7:G7) -> 1 | I7: 1909.3 | J7: Assinatura | K7: Saúde | L7: =I7/N7 -> 190.93 | M7: =IFERROR(L7/H7,"") -> 190.93 | N7: 10 | O7: 46025 | P7: =IF(N7<>1,EDATE(O7,N7-1),"") -> 46298 | Q7: =IF(O7<>"",IFERROR(DATEDIF(O7,TODAY(),"m")+1,""),"") -> 7
D8: Clube Literatura Clássica | E8: Guilherme | F8: Stella | H8: =COUNTA(E8:G8) -> 2 | I8: 1017.6 | J8: Assinatura | K8: Fixo | L8: =I8/N8 -> 84.8 | M8: =IFERROR(L8/H8,"") -> 42.4 | N8: 12 | O8: 46084 | P8: =IF(N8<>1,EDATE(O8,N8-1),"") -> 46421 | Q8: =IF(O8<>"",IFERROR(DATEDIF(O8,TODAY(),"m")+1,""),"") -> 5
D9: Hostinger Nano | E9: Guilherme | F9: Stella | H9: =COUNTA(E9:G9) -> 2 | I9: 224.24 | J9: Assinatura | K9: Serviços | L9: =I9/N9 -> 18.686667 | M9: =IFERROR(L9/H9,"") -> 9.3433333 | N9: 12 | O9: 46176 | P9: =IF(N9<>1,EDATE(O9,N9-1),"") -> 46510 | Q9: =IF(O9<>"",IFERROR(DATEDIF(O9,TODAY(),"m")+1,""),"") -> 2
D10: HBO | E10: Guilherme | F10: Stella | H10: =COUNTA(E10:G10) -> 2 | I10: 22.45 | J10: Assinatura | K10: Assinatura | L10: =I10/N10 -> 22.45 | M10: =IFERROR(L10/H10,"") -> 11.225 | N10: 1 | P10: =IF(N10<>1,EDATE(O10,N10-1),"") | Q10: =IF(O10<>"",IFERROR(DATEDIF(O10,TODAY(),"m")+1,""),"")
D11: Microsoft | E11: Guilherme | F11: Stella | H11: =COUNTA(E11:G11) -> 2 | I11: 60 | J11: Assinatura | K11: Assinaturas-Fixo | L11: =I11/N11 -> 60 | M11: =IFERROR(L11/H11,"") -> 30 | N11: 1 | P11: =IF(N11<>1,EDATE(O11,N11-1),"") | Q11: =IF(O11<>"",IFERROR(DATEDIF(O11,TODAY(),"m")+1,""),"")
D12: Seguro Tokio Marine | E12: Guilherme | F12: Stella | H12: =COUNTA(E12:G12) -> 2 | I12: 395.54 | J12: Assinatura | K12: Assinatura | L12: =I12/N12 -> 395.54 | M12: =IFERROR(L12/H12,"") -> 197.77 | N12: 1 | P12: =IF(N12<>1,EDATE(O12,N12-1),"") | Q12: =IF(O12<>"",IFERROR(DATEDIF(O12,TODAY(),"m")+1,""),"")
D13: Sem Parar | E13: Guilherme | F13: Stella | H13: =COUNTA(E13:G13) -> 2 | I13: 215 | J13: Assinatura | K13: Assinatura | L13: =I13/N13 -> 215 | M13: =IFERROR(L13/H13,"") -> 107.5 | N13: 1 | P13: =IF(N13<>1,EDATE(O13,N13-1),"") | Q13: =IF(O13<>"",IFERROR(DATEDIF(O13,TODAY(),"m")+1,""),"")
D14: Verisure | E14: Guilherme | F14: Stella | H14: =COUNTA(E14:G14) -> 2 | I14: 225 | J14: Assinatura | K14: Assinaturas-Fixo | L14: =I14/N14 -> 225 | M14: =IFERROR(L14/H14,"") -> 112.5 | N14: 1 | P14: =IF(N14<>1,EDATE(O14,N14-1),"") | Q14: =IF(O14<>"",IFERROR(DATEDIF(O14,TODAY(),"m")+1,""),"")
D15: Veroo | E15: Guilherme | F15: Stella | H15: =COUNTA(E15:G15) -> 2 | I15: 166.15 | J15: Assinatura | K15: Assinatura | L15: =I15/N15 -> 166.15 | M15: =IFERROR(L15/H15,"") -> 83.075 | N15: 1 | P15: =IF(N15<>1,EDATE(O15,N15-1),"") | Q15: =IF(O15<>"",IFERROR(DATEDIF(O15,TODAY(),"m")+1,""),"")
D16: Seguro Allianz | E16: Guilherme | H16: =COUNTA(E16:G16) -> 1 | I16: 284.05 | J16: Assinatura | K16: Fixo | L16: =I16/N16 -> 284.05 | M16: =IFERROR(L16/H16,"") -> 284.05 | N16: 1 | P16: =IF(N16<>1,EDATE(O16,N16-1),"") | Q16: =IF(O16<>"",IFERROR(DATEDIF(O16,TODAY(),"m")+1,""),"")
D17: ChatGPT | E17: Guilherme | H17: =COUNTA(E17:G17) -> 1 | I17: 110 | J17: Assinatura | K17: Serviços | L17: =I17/N17 -> 110 | M17: =IFERROR(L17/H17,"") -> 110 | N17: 1 | P17: =IF(N17<>1,EDATE(O17,N17-1),"") | Q17: =IF(O17<>"",IFERROR(DATEDIF(O17,TODAY(),"m")+1,""),"")
D18: Claude | E18: Guilherme | H18: =COUNTA(E18:G18) -> 1 | I18: 117 | J18: Assinatura | K18: AI | L18: =I18/N18 -> 117 | M18: =IFERROR(L18/H18,"") -> 117 | N18: 1 | P18: =IF(N18<>1,EDATE(O18,N18-1),"")
D19: Amazon Prime | E19: Guilherme | F19: Stella | H19: =COUNTA(E19:G19) -> 2 | I19: 19.9 | J19: Assinatura | K19: Assinatura | L19: =I19/N19 -> 19.9 | M19: =IFERROR(L19/H19,"") -> 9.95 | N19: 1 | P19: =IF(N19<>1,EDATE(O19,N19-1),"") | Q19: =IF(O19<>"",IFERROR(DATEDIF(O19,TODAY(),"m")+1,""),"")
D20: Youtube | E20: Guilherme | H20: =COUNTA(E20:G20) -> 1 | I20: 26.9 | J20: Assinatura | K20: Assinatura | L20: =I20/N20 -> 26.9 | M20: =IFERROR(L20/H20,"") -> 26.9 | N20: 1 | P20: =IF(N20<>1,EDATE(O20,N20-1),"") | Q20: =IF(O20<>"",IFERROR(DATEDIF(O20,TODAY(),"m")+1,""),"")
D21: Wellhub | E21: Guilherme | H21: =COUNTA(E21:G21) -> 1 | I21: 70 | J21: Assinatura | K21: Assinatura | L21: =I21/N21 -> 70 | M21: =IFERROR(L21/H21,"") -> 70 | N21: 1 | P21: =IF(N21<>1,EDATE(O21,N21-1),"")
D22: Muay Thai personal | E22: Guilherme | H22: =COUNTA(E22:G22) -> 1 | I22: 400 | J22: Assinatura | K22: Fixo | L22: =I22/N22 -> 400 | M22: =IFERROR(L22/H22,"") -> 400 | N22: 1 | P22: =IF(N22<>1,EDATE(O22,N22-1),"") | Q22: =IF(O22<>"",IFERROR(DATEDIF(O22,TODAY(),"m")+1,""),"")
D23: Câmera | E23: Guilherme | F23: Stella | H23: =COUNTA(E23:G23) -> 2 | I23: 22 | J23: Assinatura | K23: Fixo | L23: =I23/N23 -> 22 | M23: =IFERROR(L23/H23,"") -> 11 | N23: 1 | O23: 46206 | P23: =IF(N23<>1,EDATE(O23,N23-1),"") | Q23: =IF(O23<>"",IFERROR(DATEDIF(O23,TODAY(),"m")+1,""),"") -> 1
D24: Ração | E24: Guilherme | F24: Stella | H24: =COUNTA(E24:G24) -> 2 | I24: 392 | J24: Parcelado | K24: Fixo | L24: =I24/N24 -> 196 | M24: =IFERROR(L24/H24,"") -> 98 | N24: 2 | O24: 46056 | P24: =IF(N24<>1,EDATE(O24,N24-1),"") -> 46084 | Q24: =IF(O24<>"",IFERROR(DATEDIF(O24,TODAY(),"m")+1,""),"") -> 6
D25: Lavadora Midea | E25: Guilherme | F25: Stella | H25: =COUNTA(E25:G25) -> 2 | I25: 3219 | J25: Parcelado | K25: Produtos | L25: =I25/N25 -> 268.25 | M25: =IFERROR(L25/H25,"") -> 134.125 | N25: 12 | O25: 45903 | P25: =IF(N25<>1,EDATE(O25,N25-1),"") -> 46237 | Q25: =IF(O25<>"",IFERROR(DATEDIF(O25,TODAY(),"m")+1,""),"") -> 11
D26: Pacote Psiquiatra | E26: Guilherme | H26: =COUNTA(E26:G26) -> 1 | I26: 1700 | J26: Parcelado | K26: Saúde | L26: =I26/N26 -> 283.33333 | M26: =IFERROR(L26/H26,"") -> 283.33333 | N26: 6 | O26: 46084 | P26: =IF(N26<>1,EDATE(O26,N26-1),"") -> 46237 | Q26: =IF(O26<>"",IFERROR(DATEDIF(O26,TODAY(),"m")+1,""),"") -> 5
D27: Cinto Sabot | E27: Guilherme | H27: =COUNTA(E27:G27) -> 1 | I27: 208 | J27: Parcelado | K27: Produtos | L27: =I27/N27 -> 52 | M27: =IFERROR(L27/H27,"") -> 52 | N27: 4 | O27: 46145 | P27: =IF(N27<>1,EDATE(O27,N27-1),"") -> 46237
D28: Calça moletom | E28: Guilherme | H28: =COUNTA(E28:G28) -> 1 | I28: 128.99 | J28: Parcelado | K28: Produtos | L28: =I28/N28 -> 42.996667 | M28: =IFERROR(L28/H28,"") -> 42.996667 | N28: 3 | O28: 46176 | P28: =IF(N28<>1,EDATE(O28,N28-1),"") -> 46237 | Q28: =IF(O28<>"",IFERROR(DATEDIF(O28,TODAY(),"m")+1,""),"") -> 2
D29: Tênis Puma - A ser estornado | E29: Guilherme | H29: =COUNTA(E29:G29) -> 1 | I29: 419 | J29: Parcelado | K29: Produtos | L29: =I29/N29 -> 41.9 | M29: =IFERROR(L29/H29,"") -> 41.9 | N29: 10 | O29: 45994 | P29: =IF(N29<>1,EDATE(O29,N29-1),"") -> 46268 | Q29: =IF(O29<>"",IFERROR(DATEDIF(O29,TODAY(),"m")+1,""),"") -> 8
D30: Tênis Puma - Correto | E30: Guilherme | H30: =COUNTA(E30:G30) -> 1 | I30: 419 | J30: Parcelado | K30: Produtos | L30: =I30/N30 -> 41.9 | M30: =IFERROR(L30/H30,"") -> 41.9 | N30: 10 | O30: 45994 | P30: =IF(N30<>1,EDATE(O30,N30-1),"") -> 46268 | Q30: =IF(O30<>"",IFERROR(DATEDIF(O30,TODAY(),"m")+1,""),"") -> 8
D31: Case+Película | E31: Guilherme | H31: =COUNTA(E31:G31) -> 1 | I31: 440 | J31: Parcelado | K31: Produtos | L31: =I31/N31 -> 88 | M31: =IFERROR(L31/H31,"") -> 88 | N31: 5 | O31: 46145 | P31: =IF(N31<>1,EDATE(O31,N31-1),"") -> 46268
D32: GPS Moto | E32: Guilherme | H32: =COUNTA(E32:G32) -> 1 | I32: 313.84 | J32: Parcelado | K32: Produtos | L32: =I32/N32 -> 78.46 | M32: =IFERROR(L32/H32,"") -> 78.46 | N32: 4 | O32: 46176 | P32: =IF(N32<>1,EDATE(O32,N32-1),"") -> 46268 | Q32: =IF(O32<>"",IFERROR(DATEDIF(O32,TODAY(),"m")+1,""),"") -> 2
D33: Calça Sabot | F33: Stella | H33: =COUNTA(E33:G33) -> 1 | I33: 244.51 | J33: Parcelado | K33: Roupa | L33: =I33/N33 -> 61.1275 | M33: =IFERROR(L33/H33,"") -> 61.1275 | N33: 4 | O33: 46176 | P33: =IF(N33<>1,EDATE(O33,N33-1),"") -> 46268 | Q33: =IF(O33<>"",IFERROR(DATEDIF(O33,TODAY(),"m")+1,""),"") -> 2
D34: Revisão Royal Enfield | E34: Guilherme | H34: =COUNTA(E34:G34) -> 1 | I34: 628 | J34: Parcelado | K34: Transporte | L34: =I34/N34 -> 157 | M34: =IFERROR(L34/H34,"") -> 157 | N34: 4 | O34: 46187 | P34: =IF(N34<>1,EDATE(O34,N34-1),"") -> 46279 | Q34: =IF(O34<>"",IFERROR(DATEDIF(O34,TODAY(),"m")+1,""),"") -> 2
D35: Calça Kevlar | E35: Guilherme | H35: =COUNTA(E35:G35) -> 1 | I35: 659 | J35: Parcelado | K35: Produtos | L35: =I35/N35 -> 54.916667 | M35: =IFERROR(L35/H35,"") -> 54.916667 | N35: 12 | O35: 45964 | P35: =IF(N35<>1,EDATE(O35,N35-1),"") -> 46298 | Q35: =IF(O35<>"",IFERROR(DATEDIF(O35,TODAY(),"m")+1,""),"") -> 9
D36: Equipamentos Grid Motors | E36: Guilherme | H36: =COUNTA(E36:G36) -> 1 | I36: 2319.3 | J36: Parcelado | K36: Produtos | L36: =I36/N36 -> 193.275 | M36: =IFERROR(L36/H36,"") -> 193.275 | N36: 12 | O36: 45964 | P36: =IF(N36<>1,EDATE(O36,N36-1),"") -> 46298 | Q36: =IF(O36<>"",IFERROR(DATEDIF(O36,TODAY(),"m")+1,""),"") -> 9
D37: Racing Rabbit | E37: Guilherme | H37: =COUNTA(E37:G37) -> 1 | I37: 2000 | J37: Parcelado | K37: Moto | L37: =I37/N37 -> 166.66667 | M37: =IFERROR(L37/H37,"") -> 166.66667 | N37: 12 | O37: 45964 | P37: =IF(N37<>1,EDATE(O37,N37-1),"") -> 46298 | Q37: =IF(O37<>"",IFERROR(DATEDIF(O37,TODAY(),"m")+1,""),"") -> 9
D38: PS Plus Samuel | E38: Guilherme | F38: Stella | H38: =COUNTA(E38:G38) -> 2 | I38: 725 | J38: Parcelado | K38: Produtos | L38: =I38/N38 -> 120.83333 | M38: =IFERROR(L38/H38,"") -> 60.416667 | N38: 6 | O38: 46145 | P38: =IF(N38<>1,EDATE(O38,N38-1),"") -> 46298 | Q38: =IF(O38<>"",IFERROR(DATEDIF(O38,TODAY(),"m")+1,""),"") -> 3
D39: Capacete Stella | F39: Stella | H39: =COUNTA(E39:G39) -> 1 | I39: 973.02 | J39: Parcelado | K39: Moto | L39: =I39/N39 -> 81.085 | M39: =IFERROR(L39/H39,"") -> 81.085 | N39: 12 | O39: 45994 | P39: =IF(N39<>1,EDATE(O39,N39-1),"") -> 46329 | Q39: =IF(O39<>"",IFERROR(DATEDIF(O39,TODAY(),"m")+1,""),"") -> 8
D40: HDMI Splitter | E40: Guilherme | H40: =COUNTA(E40:G40) -> 1 | I40: 379 | J40: Parcelado | K40: Produtos | L40: =I40/N40 -> 54.142857 | M40: =IFERROR(L40/H40,"") -> 54.142857 | N40: 7 | O40: 46145 | P40: =IF(N40<>1,EDATE(O40,N40-1),"") -> 46329 | Q40: =IF(O40<>"",IFERROR(DATEDIF(O40,TODAY(),"m")+1,""),"") -> 3
D41: Caderno Azadi Store | E41: Guilherme | H41: =COUNTA(E41:G41) -> 1 | I41: 297 | J41: Parcelado | K41: Produtos | L41: =I41/N41 -> 49.5 | M41: =IFERROR(L41/H41,"") -> 49.5 | N41: 6 | O41: 46176 | P41: =IF(N41<>1,EDATE(O41,N41-1),"") -> 46329 | Q41: =IF(O41<>"",IFERROR(DATEDIF(O41,TODAY(),"m")+1,""),"") -> 2
D42: Multiprocessador | E42: Guilherme | F42: Stella | H42: =COUNTA(E42:G42) -> 2 | I42: 506 | J42: Parcelado | K42: Produtos | L42: =I42/N42 -> 50.6 | M42: =IFERROR(L42/H42,"") -> 25.3 | N42: 10 | O42: 46115 | P42: =IF(N42<>1,EDATE(O42,N42-1),"") -> 46390
D43: Jaqueta Stella | E43: Guilherme | H43: =COUNTA(E43:G43) -> 1 | I43: 1900 | J43: Parcelado | K43: Produtos | L43: =I43/N43 -> 190 | M43: =IFERROR(L43/H43,"") -> 190 | N43: 10 | O43: 46145 | P43: =IF(N43<>1,EDATE(O43,N43-1),"") -> 46421 | Q43: =IF(O43<>"",IFERROR(DATEDIF(O43,TODAY(),"m")+1,""),"") -> 3
D44: Segunda Pele Kevlar | E44: Guilherme | H44: =COUNTA(E44:G44) -> 1 | I44: 474.33 | J44: Parcelado | K44: Produtos | L44: =I44/N44 -> 52.703333 | M44: =IFERROR(L44/H44,"") -> 52.703333 | N44: 9 | O44: 46176 | P44: =IF(N44<>1,EDATE(O44,N44-1),"") -> 46421 | Q44: =IF(O44<>"",IFERROR(DATEDIF(O44,TODAY(),"m")+1,""),"") -> 2
D45: Estorno Puma | E45: Guilherme | H45: =COUNTA(E45:G45) -> 1 | I45: -42.08 | J45: Parcelado | K45: Estorno | L45: =I45/N45 -> -42.08 | M45: =IFERROR(L45/H45,"") -> -42.08 | N45: 1 | P45: =IF(N45<>1,EDATE(O45,N45-1),"") | Q45: =IF(O45<>"",IFERROR(DATEDIF(O45,TODAY(),"m")+1,""),"")
D46: Estorno Jaqueta Grid Motors | E46: Guilherme | H46: =COUNTA(E46:G46) -> 1 | I46: -64.42 | J46: Parcelado | K46: Estorno | L46: =I46/N46 -> -64.42 | M46: =IFERROR(L46/H46,"") -> -64.42 | N46: 1 | P46: =IF(N46<>1,EDATE(O46,N46-1),"") | Q46: =IF(O46<>"",IFERROR(DATEDIF(O46,TODAY(),"m")+1,""),"")
D47: Rog Ally Dock | E47: Guilherme | H47: =COUNTA(E47:G47) -> 1 | I47: 286.39 | J47: Parcelado | K47: Produtos | L47: =I47/N47 -> 28.639 | M47: =IFERROR(L47/H47,"") -> 28.639 | N47: 10 | O47: 46176 | P47: =IF(N47<>1,EDATE(O47,N47-1),"") -> 46449 | Q47: =IF(O47<>"",IFERROR(DATEDIF(O47,TODAY(),"m")+1,""),"") -> 2
D48: Wolverine Pré venda | E48: Guilherme | H48: =COUNTA(E48:G48) -> 1 | I48: 399.9 | J48: Parcelado | K48: Roupa | L48: =I48/N48 -> 57.128571 | M48: =IFERROR(L48/H48,"") -> 57.128571 | N48: 7 | O48: 46206 | P48: =IF(N48<>1,EDATE(O48,N48-1),"") -> 46390 | Q48: =IF(O48<>"",IFERROR(DATEDIF(O48,TODAY(),"m")+1,""),"") -> 1
D49: Jogos PSN | E49: Guilherme | H49: =COUNTA(E49:G49) -> 1 | I49: 372.43 | J49: Parcelado | K49: Produtos | L49: =I49/N49 -> 93.1075 | M49: =IFERROR(L49/H49,"") -> 93.1075 | N49: 4 | O49: 46206 | P49: =IF(N49<>1,EDATE(O49,N49-1),"") -> 46298 | Q49: =IF(O49<>"",IFERROR(DATEDIF(O49,TODAY(),"m")+1,""),"") -> 1
D50: Luva Fairtex | E50: Guilherme | H50: =COUNTA(E50:G50) -> 1 | I50: 1181.14 | J50: Parcelado | K50: Produtos | L50: =I50/N50 -> 118.114 | M50: =IFERROR(L50/H50,"") -> 118.114 | N50: 10 | O50: 46206 | P50: =IF(N50<>1,EDATE(O50,N50-1),"") -> 46480 | Q50: =IF(O50<>"",IFERROR(DATEDIF(O50,TODAY(),"m")+1,""),"") -> 1
D51: Pedrinho Bancos | E51: Guilherme | F51: Stella | H51: =COUNTA(E51:G51) -> 2 | I51: 1780 | J51: Parcelado | K51: Produtos | L51: =I51/N51 -> 222.5 | M51: =IFERROR(L51/H51,"") -> 111.25 | N51: 8 | P51: =IF(N51<>1,EDATE(O51,N51-1),"") -> 213 | Q51: =IF(O51<>"",IFERROR(DATEDIF(O51,TODAY(),"m")+1,""),"")
D52: Blood of the Dawnwalker | H52: =COUNTA(E52:G52) -> 0 | I52: 300 | J52: Parcelado | K52: Produtos | L52: =I52/N52 -> 50 | M52: =IFERROR(L52/H52,"") | N52: 6 | O52: 46237 | P52: =IF(N52<>1,EDATE(O52,N52-1),"") -> 46390 | Q52: =IF(O52<>"",IFERROR(DATEDIF(O52,TODAY(),"m")+1,""),"")
D53: Escapamento JBK | E53: Guilherme | H53: =COUNTA(E53:G53) -> 1 | I53: 284 | J53: Parcelado | K53: Moto | L53: =I53/N53 -> 47.333333 | M53: =IFERROR(L53/H53,"") -> 47.333333 | N53: 6 | O53: 46237 | P53: =IF(N53<>1,EDATE(O53,N53-1),"") -> 46390 | Q53: =IF(O53<>"",IFERROR(DATEDIF(O53,TODAY(),"m")+1,""),"")
D54: The Alters | E54: Guilherme | H54: =COUNTA(E54:G54) -> 1 | I54: 55 | J54: Pontual | K54: Jogos | L54: =I54/N54 -> 55 | M54: =IFERROR(L54/H54,"") -> 55 | N54: 1 | O54: 46237 | P54: =IF(N54<>1,EDATE(O54,N54-1),"") | Q54: =IF(O54<>"",IFERROR(DATEDIF(O54,TODAY(),"m")+1,""),"")
D55: Psicóloga | E55: Guilherme | H55: =COUNTA(E55:G55) -> 1 | I55: 498 | J55: pontual | K55: Saúde | L55: =I55/N55 -> 498 | M55: =IFERROR(L55/H55,"") -> 498 | N55: 1 | P55: =IF(N55<>1,EDATE(O55,N55-1),"") | Q55: =IF(O55<>"",IFERROR(DATEDIF(O55,TODAY(),"m")+1,""),"")
D56: Bonfas Chope | E56: Guilherme | F56: Stella | H56: =COUNTA(E56:G56) -> 2 | I56: 40 | J56: Pontual | K56: Cm | L56: =I56/N56 -> 40 | M56: =IFERROR(L56/H56,"") -> 20 | N56: 1 | P56: =IF(N56<>1,EDATE(O56,N56-1),"") | Q56: =IF(O56<>"",IFERROR(DATEDIF(O56,TODAY(),"m")+1,""),"")
D57: Bonfas Lanche | E57: Guilherme | H57: =COUNTA(E57:G57) -> 1 | I57: 32 | L57: =I57/N57 -> 32 | M57: =IFERROR(L57/H57,"") -> 32 | N57: 1 | P57: =IF(N57<>1,EDATE(O57,N57-1),"") | Q57: =IF(O57<>"",IFERROR(DATEDIF(O57,TODAY(),"m")+1,""),"")
D58: Remédios Stella | F58: Stella | H58: =COUNTA(E58:G58) -> 1 | I58: 166 | L58: =I58/N58 -> 166 | M58: =IFERROR(L58/H58,"") -> 166 | N58: 1 | P58: =IF(N58<>1,EDATE(O58,N58-1),"") | Q58: =IF(O58<>"",IFERROR(DATEDIF(O58,TODAY(),"m")+1,""),"")
D59: Ração Brida | E59: Guilherme | F59: Stella | H59: =COUNTA(E59:G59) -> 2 | I59: 74 | L59: =I59/N59 -> 74 | M59: =IFERROR(L59/H59,"") -> 37 | N59: 1 | P59: =IF(N59<>1,EDATE(O59,N59-1),"") | Q59: =IF(O59<>"",IFERROR(DATEDIF(O59,TODAY(),"m")+1,""),"")
D60: Pagamento Ração Brida | E60: Guilherme | H60: =COUNTA(E60:G60) -> 1 | I60: -37 | L60: =I60/N60 -> -37 | M60: =IFERROR(L60/H60,"") -> -37 | N60: 1 | P60: =IF(N60<>1,EDATE(O60,N60-1),"") | Q60: =IF(O60<>"",IFERROR(DATEDIF(O60,TODAY(),"m")+1,""),"")
C61: TENTAR ADIATNAR | D61: Moletom Brutal Kill | E61: Guilherme | H61: =COUNTA(E61:G61) -> 1 | I61: 279 | J61: Parcelado | L61: =I61/N61 -> 27.9 | M61: =IFERROR(L61/H61,"") -> 27.9 | N61: 10 | O61: 46237 | P61: =IF(N61<>1,EDATE(O61,N61-1),"") -> 46510 | Q61: =IF(O61<>"",IFERROR(DATEDIF(O61,TODAY(),"m")+1,""),"")
D62: Uber Mr. Jones | E62: Guilherme | F62: Stella | H62: =COUNTA(E62:G62) -> 2 | I62: 36 | L62: =I62/N62 -> 36 | M62: =IFERROR(L62/H62,"") -> 18 | N62: 1 | P62: =IF(N62<>1,EDATE(O62,N62-1),"") | Q62: =IF(O62<>"",IFERROR(DATEDIF(O62,TODAY(),"m")+1,""),"")
D63: Gibs | E63: Guilherme | H63: =COUNTA(E63:G63) -> 1 | I63: 35 | L63: =I63/N63 -> 35 | M63: =IFERROR(L63/H63,"") -> 35 | N63: 1 | P63: =IF(N63<>1,EDATE(O63,N63-1),"") | Q63: =IF(O63<>"",IFERROR(DATEDIF(O63,TODAY(),"m")+1,""),"")
D64: Serviço de nuvem da câmera | E64: Guilherme | F64: Stella | H64: =COUNTA(E64:G64) -> 2 | I64: 75 | L64: =I64/N64 -> 75 | M64: =IFERROR(L64/H64,"") -> 37.5 | N64: 1 | P64: =IF(N64<>1,EDATE(O64,N64-1),"") | Q64: =IF(O64<>"",IFERROR(DATEDIF(O64,TODAY(),"m")+1,""),"")
D65: Rappi | E65: Guilherme | F65: Stella | H65: =COUNTA(E65:G65) -> 2 | I65: 74 | L65: =I65/N65 -> 74 | M65: =IFERROR(L65/H65,"") -> 37 | N65: 1 | P65: =IF(N65<>1,EDATE(O65,N65-1),"") | Q65: =IF(O65<>"",IFERROR(DATEDIF(O65,TODAY(),"m")+1,""),"")
D66: Gasolina | F66: Stella | H66: =COUNTA(E66:G66) -> 1 | I66: 107.5 | L66: =I66/N66 -> 107.5 | M66: =IFERROR(L66/H66,"") -> 107.5 | N66: 1 | P66: =IF(N66<>1,EDATE(O66,N66-1),"") | Q66: =IF(O66<>"",IFERROR(DATEDIF(O66,TODAY(),"m")+1,""),"")
D67: Gasolina | E67: Guilherme | H67: =COUNTA(E67:G67) -> 1 | I67: 37.5 | L67: =I67/N67 -> 37.5 | M67: =IFERROR(L67/H67,"") -> 37.5 | N67: 1 | P67: =IF(N67<>1,EDATE(O67,N67-1),"") | Q67: =IF(O67<>"",IFERROR(DATEDIF(O67,TODAY(),"m")+1,""),"")
D68: Lanche | E68: Guilherme | H68: =COUNTA(E68:G68) -> 1 | I68: 50 | L68: =I68/N68 -> 50 | M68: =IFERROR(L68/H68,"") -> 50 | N68: 1 | P68: =IF(N68<>1,EDATE(O68,N68-1),"") | Q68: =IF(O68<>"",IFERROR(DATEDIF(O68,TODAY(),"m")+1,""),"")
D69: Gibis | E69: Guilherme | H69: =COUNTA(E69:G69) -> 1 | I69: 35 | L69: =I69/N69 -> 35 | M69: =IFERROR(L69/H69,"") -> 35 | N69: 1 | P69: =IF(N69<>1,EDATE(O69,N69-1),"") | Q69: =IF(O69<>"",IFERROR(DATEDIF(O69,TODAY(),"m")+1,""),"")
D70: Bonffas Beer | E70: Guilherme | H70: =COUNTA(E70:G70) -> 1 | I70: 52.14 | L70: =I70/N70 -> 52.14 | M70: =IFERROR(L70/H70,"") -> 52.14 | N70: 1 | P70: =IF(N70<>1,EDATE(O70,N70-1),"") | Q70: =IF(O70<>"",IFERROR(DATEDIF(O70,TODAY(),"m")+1,""),"")
D71: Gasolina Pirassunusng | E71: Guilherme | F71: Stella | H71: =COUNTA(E71:G71) -> 2 | I71: 130.01 | L71: =I71/N71 -> 130.01 | M71: =IFERROR(L71/H71,"") -> 65.005 | N71: 1 | P71: =IF(N71<>1,EDATE(O71,N71-1),"") | Q71: =IF(O71<>"",IFERROR(DATEDIF(O71,TODAY(),"m")+1,""),"")
D72: Hot Wheels | E72: Guilherme | H72: =COUNTA(E72:G72) -> 1 | I72: 99 | L72: =I72/N72 -> 99 | M72: =IFERROR(L72/H72,"") -> 99 | N72: 1 | P72: =IF(N72<>1,EDATE(O72,N72-1),"") | Q72: =IF(O72<>"",IFERROR(DATEDIF(O72,TODAY(),"m")+1,""),"")
D73: Pagamento Hot Wheels | E73: Guilherme | H73: =COUNTA(E73:G73) -> 1 | I73: -99 | L73: =I73/N73 -> -99 | M73: =IFERROR(L73/H73,"") -> -99 | N73: 1 | P73: =IF(N73<>1,EDATE(O73,N73-1),"") | Q73: =IF(O73<>"",IFERROR(DATEDIF(O73,TODAY(),"m")+1,""),"")
D74: Kikão | E74: Guilherme | F74: Stella | H74: =COUNTA(E74:G74) -> 2 | I74: 139 | L74: =I74/N74 -> 139 | M74: =IFERROR(L74/H74,"") -> 69.5 | N74: 1 | P74: =IF(N74<>1,EDATE(O74,N74-1),"") | Q74: =IF(O74<>"",IFERROR(DATEDIF(O74,TODAY(),"m")+1,""),"")
D75: Gasolina de Volta | F75: Stella | H75: =COUNTA(E75:G75) -> 1 | I75: 100 | L75: =I75/N75 -> 100 | M75: =IFERROR(L75/H75,"") -> 100 | N75: 1 | P75: =IF(N75<>1,EDATE(O75,N75-1),"") | Q75: =IF(O75<>"",IFERROR(DATEDIF(O75,TODAY(),"m")+1,""),"")
D76: Odisseia | E76: Guilherme | F76: Stella | H76: =COUNTA(E76:G76) -> 2 | I76: 90 | L76: =I76/N76 -> 90 | M76: =IFERROR(L76/H76,"") -> 45 | N76: 1 | P76: =IF(N76<>1,EDATE(O76,N76-1),"") | Q76: =IF(O76<>"",IFERROR(DATEDIF(O76,TODAY(),"m")+1,""),"")
D77: Pagamento Odisseia | E77: Guilherme | H77: =COUNTA(E77:G77) -> 1 | I77: -45 | L77: =I77/N77 -> -45 | M77: =IFERROR(L77/H77,"") -> -45 | N77: 1 | P77: =IF(N77<>1,EDATE(O77,N77-1),"") | Q77: =IF(O77<>"",IFERROR(DATEDIF(O77,TODAY(),"m")+1,""),"")
H78: =COUNTA(E78:G78) -> 0 | L78: =I78/N78 -> 0 | M78: =IFERROR(L78/H78,"") | N78: 1 | P78: =IF(N78<>1,EDATE(O78,N78-1),"") | Q78: =IF(O78<>"",IFERROR(DATEDIF(O78,TODAY(),"m")+1,""),"")
H79: =COUNTA(E79:G79) -> 0 | L79: =I79/N79 -> 0 | M79: =IFERROR(L79/H79,"") | N79: 1 | P79: =IF(N79<>1,EDATE(O79,N79-1),"") | Q79: =IF(O79<>"",IFERROR(DATEDIF(O79,TODAY(),"m")+1,""),"")
H80: =COUNTA(E80:G80) -> 0 | L80: =I80/N80 -> 0 | M80: =IFERROR(L80/H80,"") | N80: 1 | P80: =IF(N80<>1,EDATE(O80,N80-1),"") | Q80: =IF(O80<>"",IFERROR(DATEDIF(O80,TODAY(),"m")+1,""),"")
H81: =COUNTA(E81:G81) -> 0 | L81: =I81/N81 -> 0 | M81: =IFERROR(L81/H81,"") | N81: 1 | P81: =IF(N81<>1,EDATE(O81,N81-1),"") | Q81: =IF(O81<>"",IFERROR(DATEDIF(O81,TODAY(),"m")+1,""),"")
H82: =COUNTA(E82:G82) -> 0 | L82: =I82/N82 -> 0 | M82: =IFERROR(L82/H82,"") | N82: 1 | P82: =IF(N82<>1,EDATE(O82,N82-1),"") | Q82: =IF(O82<>"",IFERROR(DATEDIF(O82,TODAY(),"m")+1,""),"")
H83: =COUNTA(E83:G83) -> 0 | L83: =I83/N83 -> 0 | M83: =IFERROR(L83/H83,"") | N83: 1 | P83: =IF(N83<>1,EDATE(O83,N83-1),"") | Q83: =IF(O83<>"",IFERROR(DATEDIF(O83,TODAY(),"m")+1,""),"")
H84: =COUNTA(E84:G84) -> 0 | L84: =I84/N84 -> 0 | M84: =IFERROR(L84/H84,"") | N84: 1 | P84: =IF(N84<>1,EDATE(O84,N84-1),"") | Q84: =IF(O84<>"",IFERROR(DATEDIF(O84,TODAY(),"m")+1,""),"")
H85: =COUNTA(E85:G85) -> 0 | L85: =I85/N85 -> 0 | M85: =IFERROR(L85/H85,"") | N85: 1 | P85: =IF(N85<>1,EDATE(O85,N85-1),"") | Q85: =IF(O85<>"",IFERROR(DATEDIF(O85,TODAY(),"m")+1,""),"")
H86: =COUNTA(E86:G86) -> 0 | L86: =I86/N86 -> 0 | M86: =IFERROR(L86/H86,"") | N86: 1 | P86: =IF(N86<>1,EDATE(O86,N86-1),"") | Q86: =IF(O86<>"",IFERROR(DATEDIF(O86,TODAY(),"m")+1,""),"")
H87: =COUNTA(E87:G87) -> 0 | L87: =I87/N87 -> 0 | M87: =IFERROR(L87/H87,"") | N87: 1 | P87: =IF(N87<>1,EDATE(O87,N87-1),"") | Q87: =IF(O87<>"",IFERROR(DATEDIF(O87,TODAY(),"m")+1,""),"")
H88: =COUNTA(E88:G88) -> 0 | L88: =I88/N88 -> 0 | M88: =IFERROR(L88/H88,"") | N88: 1 | P88: =IF(N88<>1,EDATE(O88,N88-1),"") | Q88: =IF(O88<>"",IFERROR(DATEDIF(O88,TODAY(),"m")+1,""),"")
H89: =COUNTA(E89:G89) -> 0 | L89: =I89/N89 -> 0 | M89: =IFERROR(L89/H89,"") | N89: 1 | P89: =IF(N89<>1,EDATE(O89,N89-1),"") | Q89: =IF(O89<>"",IFERROR(DATEDIF(O89,TODAY(),"m")+1,""),"")
... H149: =COUNTA(E149:G149) -> 0 | L149: =I149/N149 -> 0 | M149: =IFERROR(L149/H149,"") | N149: 1 | P149: =IF(N149<>1,EDATE(O149,N149-1),"") | Q149: =IF(O149<>"",IFERROR(DATEDIF(O149,TODAY(),"m")+1,""),"")

Sheet Contas
D2: Descrição | E2: Responsável 1 | F2: Responsável 2 | G2: Responsável 3 | H2: Divisão | I2: Valor Total | J2: Valor da Parcela | K2: Valor por responsável | L2: Parcelas | M2: Primeira Parcela | N2: Última Parcela | O2: Parcelas pagas (vira todo dia 10)
D3: Aluguel | E3: Guilherme | F3: Stella | H3: =COUNTA(E3:G3) -> 2 | I3: 3235.67 | J3: =I3/L3 -> 3235.67 | K3: =IFERROR(J3/H3,"") -> 1617.835 | L3: =(DATEDIF(M3,N3,"m")+1) -> 1 | O3: =IFERROR(DATEDIF(M3,TODAY(),"m")+1,"") -> 1519
D4: Vivo | E4: Guilherme | F4: Stella | H4: =COUNTA(E4:F4) -> 2 | I4: 444 | J4: =I4/L4 -> 444 | K4: =IFERROR(J4/H4,"") -> 222 | L4: =(DATEDIF(M4,N4,"m")+1) -> 1 | O4: =IFERROR(DATEDIF(M4,TODAY(),"m")+1,"") -> 1519
B5: Guilherme | D5: Luz | E5: Guilherme | F5: Stella | H5: =COUNTA(E5:F5) -> 2 | I5: 360 | J5: =I5/L5 -> 360 | K5: =IFERROR(J5/H5,"") -> 180 | L5: =(DATEDIF(M5,N5,"m")+1) -> 1 | O5: =IFERROR(DATEDIF(M5,TODAY(),"m")+1,"") -> 1519
B6: =SUMIF($E$3:$E$34,B5,$K$3:$K$34) -> 2382.07 | D6: Água | E6: Guilherme | F6: Stella | H6: =COUNTA(E6:F6) -> 2 | I6: 86.7 | J6: =I6/L6 -> 86.7 | K6: =IFERROR(J6/H6,"") -> 43.35 | L6: =(DATEDIF(M6,N6,"m")+1) -> 1 | O6: =IFERROR(DATEDIF(M6,TODAY(),"m")+1,"") -> 1519
D7: Gás | E7: Guilherme | F7: Stella | H7: =COUNTA(E7:F7) -> 2 | I7: 46 | J7: =I7/L7 -> 46 | K7: =IFERROR(J7/H7,"") -> 23 | L7: =(DATEDIF(M7,N7,"m")+1) -> 1 | O7: =IFERROR(DATEDIF(M7,TODAY(),"m")+1,"") -> 1519
B8: Stella | D8: Verisure | E8: Guilherme | F8: Stella | H8: =COUNTA(E8:F8) -> 2 | I8: 224.77 | J8: =I8/L8 -> 224.77 | K8: =IFERROR(J8/H8,"") -> 112.385 | L8: =(DATEDIF(M8,N8,"m")+1) -> 1 | O8: =IFERROR(DATEDIF(M8,TODAY(),"m")+1,"") -> 1519
B9: =SUMIF($F$3:$F$34,B8,$K$3:$K$34) -> 3382.07 | D9: Seguranças+Câmera+Seguro Residencial | E9: Guilherme | F9: Stella | H9: =COUNTA(E9:G9) -> 2 | I9: =250+117 -> 367 | J9: =I9/L9 -> 367 | K9: =IFERROR(J9/H9,"") -> 183.5 | L9: =(DATEDIF(M9,N9,"m")+1) -> 1 | O9: =IFERROR(DATEDIF(M9,TODAY(),"m")+1,"") -> 1519
D10: Cartão Itaú da Stella | F10: Stella | H10: =COUNTA(E10:G10) -> 1 | I10: 1000 | J10: =I10/L10 -> 1000 | K10: =IFERROR(J10/H10,"") -> 1000 | L10: =(DATEDIF(M10,N10,"m")+1) -> 1 | O10: =IFERROR(DATEDIF(M10,TODAY(),"m")+1,"") -> 1519

Sheet NuConta e Poupança
N1: Dinheiro guardado para...
L3: Saldo inicial | M3: Para retirar mês que vem? | N3: =SUM(N5:N21) -> 5351
L4: Movimentação
L5: Adiantamento Salário | N5: 4912
L6: Seguro | N6: 101
L8: Reembolso Psicóloga | M8: Sim | N8: 338
F9: Total
E10: Com turbo | F10: =SUM(G11:I11) -> 164.15 | G10: Caixinha Guilherme | H10: Caixinha Stella | I10: Detran
E11: Sem turbo | F11: =SUM(G11:H11) -> 164.15 | G11: =G12+SUM(G14:G496) -> 164.15 | H11: =H12+SUM(H14:H496) -> 0 | I11: =I12+SUM(I14:I496) -> 0
F12: Saldo inicial | G12: 15250
F13: Movimentação
F14: IPVAs + Licenciamento
F15: Tirando da Caixinha Turbo | G15: 773.35
F16: Adiantamento Stella Janeiro | G16: -5148
F17: Ajuste NuConta | G17: -168
F18: Cidadania+Veterinário Brida | G18: -1700
F19: Devolução Stella | G19: 5148
F20: Salário afastamento | G20: -4938
F21: Emergência Geleia+Vurtuoso+Terra Brasa | G21: -1595
F22: Adiantamento Stella | G22: -4677
F23: Galpãozin | G23: -200
F24: Devolução Stella | G24: 4677
F25: Fisioterapia Stella | G25: -750
F26: Pagamento Fasolina + Almoço Shirley + Linkedin+Bonfas | G26: -652
... F72: Recolhimento Receita | G72: -1572
B75: Devolução Stella | C75: 4433
B76: Ilumeo Julho - 1º PPT | C76: 8000
B78: Control+Dawnwalker | C78: -90
B79: Agosto | C79: 1000 | D79: 300
B80: Ilumeo Agosto - 2º PPT | C80: 8000
B82: Control+Dawnwalker | C82: -90
B83: Setembro | C83: 2000 | D83: 300
B84: Passagens - Compradas em agosto | C84: -12807
B86: Restituição IR | C86: 5520
B88: Outubro | C88: 2000 | D88: 300
B89: Control+Dawnwalker | C89: -90
B90: Pagamento Control | C90: 240
B92: Novembro | C92: 2000 | D92: 300
B93: Dawnwalker | C93: -50
B94: Pagamento Dawnwalker | C94: 300
B96: Dezembro | C96: 2000 | D96: 300
B97: Ilumeo Dezembro - 3º PPT | C97: 8000
B98: Segunda Parcela 13º | C98: 4180
B100: Janeiro | C100: 2000 | D100: 300
B101: Fevereiro | C101: 2000 | D101: 300
B102: Março | C102: 2000 | D102: 300
B104: Dinheiro para Europa | C104: -20000
B106: Abril | C106: 2000 | D106: 300
B107: Maio | C107: 2000 | D107: 300
B108: Ilumeo Maio - 4º PPT | C108: 8000
B109: Junho | C109: 2000 | D109: 300
B110: Julho | C110: 2000 | D110: 300

Sheet Checklist de pagamento
B1: Conta | C1: Pago? | D1: Obs.
B2: Aluguel | C2: OK
B3: Vivo | C3: OK
B4: Luz | C4: Ok
B5: Água | C5: OK
B6: Gás | C6: Ok
B7: Câmeras | C7: Ok
B8: NuBank | C8: Ok
B9: Seu João
B10: Dera | C10: OK
